Metadata-Version: 2.1
Name: djinni-build
Version: 1.0.0
Summary: Utility to package and distribute Djinni libraries easily.
Home-page: https://github.com/jothepro/djinni_build
Author: jothepro
Author-email: djinni_build@jothe.pro
License: MIT
Keywords: djinni
Platform: UNKNOWN
Classifier: Intended Audience :: Developers
Classifier: License :: OSI Approved :: MIT License
Classifier: Programming Language :: Python :: 3
Classifier: Programming Language :: Python :: 3.10
Requires-Python: >=3.10
License-File: LICENSE
